LICENSE
README.rst
setup.cfg
setup.py
linkedin_scraperb/__init__.py
linkedin_scraperb/actions.py
linkedin_scraperb/company.py
linkedin_scraperb/constants.py
linkedin_scraperb/job_search.py
linkedin_scraperb/jobs.py
linkedin_scraperb/objects.py
linkedin_scraperb/person.py
linkedin_scraperb/selectors.py
linkedin_scraperb.egg-info/PKG-INFO
linkedin_scraperb.egg-info/SOURCES.txt
linkedin_scraperb.egg-info/dependency_links.txt
linkedin_scraperb.egg-info/requires.txt
linkedin_scraperb.egg-info/top_level.txt