Metadata-Version: 2.1
Name: linkedin-scraperb
Version: 0.0.5
Summary: Scrapes user data from Linkedin (this is a branch)
Home-page: https://github.com/RRohjansRsm/linkedin_scraper
Download-URL: https://github.com/RRohjansRsm/linkedin_scraper/archive/refs/tags/0.0.5.tar.gz
Author: Joey Sham
Author-email: sham.joey@gmail.com
Keywords: linkedin,scraping,scraper
License-File: LICENSE
